ml_idm/__init__.py
ml_idm/core/__init__.py
ml_idm/core/cols_meta.py
ml_idm/core/dependencies.py
ml_idm/core/inputs_cache.py
ml_idm/core/model_wrapper.py
ml_idm/core/reader/abstract_reader.py
ml_idm/core/reader/reader.py
ml_idm/core/reader/path_providers/local.py
ml_idm/core/reader/path_providers/path_provider.py
ml_idm/core/utils/common_utils.py
ml_idm/core/utils/ui_utils.py
ml_idm/ext/reader/st_reader.py
ml_idm/ext/reader/path_providers/gs.py
ml_idm/ext/shap/shap_wrapper.py
ml_idm/ext/shap/utils.py
ml_idm/ext/shap/ui/__init__.py
ml_idm/ext/shap/ui/st.py
ml_idm/ui/__init__.py
ml_idm/ui/st.py
ml_idm-0.0.2.dist-info/METADATA
ml_idm-0.0.2.dist-info/WHEEL
ml_idm-0.0.2.dist-info/top_level.txt
ml_idm-0.0.2.dist-info/RECORD
